cardberg/__init__.py
cardberg/error.py
cardberg/resource.py
cardberg/version.py
cardberg-0.2.0.dist-info/LICENSE
cardberg-0.2.0.dist-info/METADATA
cardberg-0.2.0.dist-info/WHEEL
cardberg-0.2.0.dist-info/top_level.txt
cardberg-0.2.0.dist-info/RECORD
